{
  "config": {
    "cdap": {
      "version": "4.0.0-1"
    },
    "hadoop": {
      "hdfs_site": {
        "dfs.namenode.delegation.token.renew-interval": "600000",
        "dfs.namenode.delegation.token.max-lifetime": "600000"
      },
      "mapred_site": {
        "mapreduce.task.io.sort.mb": "100"
      },
      "yarn_site": {
        "yarn.nodemanager.delete.debug-delay-sec": "43200"
      }
    },
    "hbase": {
      "hbase_site": {
        "hbase.auth.key.update.interval": "600000"
      }
    }
  },
  "services": "generic-users",
  "initial-lease-duration": 82800000
}
